{
  "success": true,
  "last_updated": "2026-05-22T12:27:06.210Z",
  "data": {
    "version_number": "1.19.51",
    "update_title": "Standard Release",
    "description": "1.19.51 is a hotfix to Bedrock Edition released on December 13-15, 2022, which fixes bugs.",
    "server_version": "1.19.52.01",
    "download_urls": {
      "linux": "https://www.minecraft.net/bedrockdedicatedserver/bin-linux/bedrock-server-1.19.52.01.zip",
      "windows": "https://www.minecraft.net/bedrockdedicatedserver/bin-win/bedrock-server-1.19.52.01.zip"
    },
    "scraped_preview": true
  }
}